{"config":{"schema":"https://moonrepo.dev/schemas/project.json","dependsOn":[],"docker":{"file":{"buildTask":null,"image":null,"startTask":null},"scaffold":{"include":[]}},"env":{},"fileGroups":{},"id":null,"language":"unknown","layer":"unknown","owners":{"customGroups":{},"defaultOwner":null,"optional":false,"paths":[],"requiredApprovals":null},"platform":null,"project":null,"stack":"unknown","tags":[],"tasks":{"build":{"extends":null,"description":null,"command":"pnpm build","args":null,"deps":null,"env":null,"globalInputs":[],"inputs":[{"glob":"src/**/*","cache":true}],"local":null,"outputs":[{"file":".next"}],"options":{"affectedFiles":null,"affectedPassInputs":null,"allowFailure":null,"cache":null,"cacheKey":null,"cacheLifetime":null,"envFile":null,"inferInputs":null,"interactive":null,"internal":null,"merge":null,"mergeArgs":null,"mergeDeps":null,"mergeEnv":null,"mergeInputs":null,"mergeOutputs":null,"mutex":null,"os":null,"outputStyle":null,"persistent":null,"priority":null,"retryCount":null,"runDepsInParallel":null,"runInCI":null,"runFromWorkspaceRoot":null,"shell":null,"timeout":null,"unixShell":null,"windowsShell":null},"platform":"unknown","preset":null,"script":null,"toolchain":[],"type":null},"lint":{"extends":null,"description":null,"command":"pnpm lint","args":null,"deps":null,"env":null,"globalInputs":[],"inputs":[{"glob":"src/**/*","cache":true}],"local":null,"outputs":null,"options":{"affectedFiles":null,"affectedPassInputs":null,"allowFailure":null,"cache":null,"cacheKey":null,"cacheLifetime":null,"envFile":null,"inferInputs":null,"interactive":null,"internal":null,"merge":null,"mergeArgs":null,"mergeDeps":null,"mergeEnv":null,"mergeInputs":null,"mergeOutputs":null,"mutex":null,"os":null,"outputStyle":null,"persistent":null,"priority":null,"retryCount":null,"runDepsInParallel":null,"runInCI":null,"runFromWorkspaceRoot":null,"shell":null,"timeout":null,"unixShell":null,"windowsShell":null},"platform":"unknown","preset":null,"script":null,"toolchain":[],"type":null},"start":{"extends":null,"description":null,"command":"pnpm start","args":null,"deps":null,"env":null,"globalInputs":[],"inputs":[{"glob":".next/**/*","cache":true}],"local":null,"outputs":[{"glob":".next/**/*"}],"options":{"affectedFiles":null,"affectedPassInputs":null,"allowFailure":null,"cache":null,"cacheKey":null,"cacheLifetime":null,"envFile":null,"inferInputs":null,"interactive":null,"internal":null,"merge":null,"mergeArgs":null,"mergeDeps":null,"mergeEnv":null,"mergeInputs":null,"mergeOutputs":null,"mutex":null,"os":null,"outputStyle":null,"persistent":null,"priority":null,"retryCount":null,"runDepsInParallel":null,"runInCI":null,"runFromWorkspaceRoot":null,"shell":null,"timeout":null,"unixShell":null,"windowsShell":null},"platform":"unknown","preset":null,"script":null,"toolchain":[],"type":null}},"toolchain":{"default":null,"bun":null,"deno":null,"python":null,"node":null,"rust":null,"plugins":{}},"workspace":{"inheritedTasks":{"exclude":[],"include":null,"rename":{}}}},"id":"dashboard","inherited":{"order":["*","typescript","node"],"config":{"schema":"https://moonrepo.dev/schemas/tasks.json","extends":null,"fileGroups":{},"implicitDeps":[],"implicitInputs":[],"tasks":{},"taskOptions":null},"layers":{},"taskLayers":{}},"language":"typescript","layer":"unknown","platform":"unknown","root":"/Users/bilolwabona/Dev/bilo-mono/apps/frontend/dashboard","source":"apps/frontend/dashboard","stack":"unknown","tasks":{"build":{"args":["build"],"command":"pnpm","id":"build","inputs":[{"glob":"src/**/*","cache":true},{"glob":"/.moon/*.{pkl,yml}","cache":true}],"inputGlobs":{"apps/frontend/dashboard/src/**/*":{"cache":true},".moon/*.{pkl,yml}":{"cache":true}},"options":{"affectedPassInputs":false,"allowFailure":false,"cache":true,"inferInputs":true,"internal":false,"interactive":false,"mergeArgs":"append","mergeDeps":"append","mergeEnv":"append","mergeInputs":"append","mergeOutputs":"append","persistent":false,"priority":"normal","retryCount":0,"runDepsInParallel":true,"runInCI":"affected","runFromWorkspaceRoot":false,"shell":true},"outputs":[{"file":".next"}],"outputFiles":{"apps/frontend/dashboard/.next":{"optional":false}},"platform":"unknown","state":{"expanded":true},"target":"dashboard:build","toolchains":["system"],"type":"build"},"lint":{"args":["lint"],"command":"pnpm","id":"lint","inputs":[{"glob":"src/**/*","cache":true},{"glob":"/.moon/*.{pkl,yml}","cache":true}],"inputGlobs":{"apps/frontend/dashboard/src/**/*":{"cache":true},".moon/*.{pkl,yml}":{"cache":true}},"options":{"affectedPassInputs":false,"allowFailure":false,"cache":true,"inferInputs":true,"internal":false,"interactive":false,"mergeArgs":"append","mergeDeps":"append","mergeEnv":"append","mergeInputs":"append","mergeOutputs":"append","persistent":false,"priority":"normal","retryCount":0,"runDepsInParallel":true,"runInCI":"affected","runFromWorkspaceRoot":false,"shell":true},"platform":"unknown","state":{"expanded":true},"target":"dashboard:lint","toolchains":["system"],"type":"test"},"start":{"args":["start"],"command":"pnpm","id":"start","inputs":[{"glob":".next/**/*","cache":true},{"glob":"/.moon/*.{pkl,yml}","cache":true}],"inputGlobs":{".moon/*.{pkl,yml}":{"cache":true}},"options":{"affectedPassInputs":false,"allowFailure":false,"cache":false,"inferInputs":true,"internal":false,"interactive":false,"mergeArgs":"append","mergeDeps":"append","mergeEnv":"append","mergeInputs":"append","mergeOutputs":"append","outputStyle":"stream","persistent":true,"priority":"normal","retryCount":0,"runDepsInParallel":true,"runInCI":false,"runFromWorkspaceRoot":false,"shell":true},"outputs":[{"glob":".next/**/*"}],"outputGlobs":{"apps/frontend/dashboard/.next/**/*":{}},"platform":"unknown","preset":"server","state":{"expanded":true,"localOnly":true},"target":"dashboard:start","toolchains":["system"],"type":"build"}},"taskTargets":["dashboard:build","dashboard:lint","dashboard:start"],"toolchains":["system"]}